LICENSE.md
bible_alignments/.github/actions/run-checks/action.yml
bible_alignments/.github/actions/setup-poetry-env/action.yml
bible_alignments/.github/workflows/on-merge-to-main.yml
bible_alignments/.github/workflows/on-pull-request.yml
bible_alignments/.github/workflows/on-release-main.yml
bible_alignments/.github/workflows/validate-codecov-config.yml
bible_alignments/__init__.py
bible_alignments/burrito/AlignmentGroup.py
bible_alignments/burrito/AlignmentSet.py
bible_alignments/burrito/AlignmentType.py
bible_alignments/burrito/BadRecord.py
bible_alignments/burrito/BaseToken.py
bible_alignments/burrito/VerseData.py
bible_alignments/burrito/__init__.py
bible_alignments/burrito/alignments.py
bible_alignments/burrito/manager.py
bible_alignments/burrito/source.py
bible_alignments/burrito/target.py
bible_alignments/burrito/util.py
bible_alignments/catalog.py
bible_alignments/notebooks/01-Exploration.ipynb
bible_alignments/strongs.py
data/eng/alignments/BSB/SBLGNT-BSB-manual.json
data/eng/alignments/BSB/SBLGNT-BSB-manual.toml
data/eng/targets/BSB/nt_BSB.tsv
data/eng/targets/BSB/ot_BSB.tsv
data/sources/SBLGNT.tsv
bible_alignments-0.4.2.dist-info/LICENSE.md
bible_alignments-0.4.2.dist-info/METADATA
bible_alignments-0.4.2.dist-info/WHEEL
bible_alignments-0.4.2.dist-info/RECORD
