Metadata-Version: 2.1
Name: bible-alignments
Version: 0.4.2
Summary: Word-level alignments for Bibles, including both automatic alignments and manually corrected alignments.
Home-page: https://github.com/Clear-Bible/Alignments
License: MIT
Keywords: Bible,alignment,Bible alignment
Author: Sean Boisen
Author-email: sean.boisen@biblica.com
Requires-Python: >=3.9,<3.12
Classifier: Development Status :: 4 - Beta
Classifier: Intended Audience :: Religion
Classifier: License :: OSI Approved :: MIT License
Classifier: Operating System :: OS Independent
Classifier: Programming Language :: Python :: 3
Classifier: Programming Language :: Python :: 3.9
Classifier: Programming Language :: Python :: 3.10
Classifier: Programming Language :: Python :: 3.11
Classifier: Topic :: Religion
Classifier: Topic :: Software Development :: Libraries :: Python Modules
Requires-Dist: biblelib (>=0.3)
Requires-Dist: django (>=4.2.2,<5.0.0)
Requires-Dist: django-environ (>=0.10.0,<0.11.0)
Requires-Dist: djangorestframework (>=3.14.0,<4.0.0)
Requires-Dist: jsonlines (>=3.1.0,<4.0.0)
Requires-Dist: jupyterlab (>=3.6.1,<4.0.0)
Requires-Dist: pandas (>=2.1.0,<3.0.0)
Requires-Dist: pydantic (>=2.1.1,<3.0.0)
Requires-Dist: tomli (>=2.0.1,<3.0.0)
Requires-Dist: unicodecsv (>=0.14.1,<0.15.0)
Project-URL: Repository, https://github.com/Clear-Bible/Alignments
